setup.py
django_sunlightcongress.egg-info/PKG-INFO
django_sunlightcongress.egg-info/SOURCES.txt
django_sunlightcongress.egg-info/dependency_links.txt
django_sunlightcongress.egg-info/requires.txt
django_sunlightcongress.egg-info/top_level.txt
sunlightcongress/__init__.py
sunlightcongress/admin.py
sunlightcongress/choices.py
sunlightcongress/managers.py
sunlightcongress/models.py
sunlightcongress/settings.py
sunlightcongress/management/__init__.py
sunlightcongress/management/commands/__init__.py
sunlightcongress/management/commands/congress.py
sunlightcongress/migrations/0001_initial.py
sunlightcongress/migrations/__init__.py