Metadata-Version: 1.0
Name: django-sunlightcongress
Version: 0.1
Summary: A Django interface to the Sunlight Foundation Congress API
Home-page: https://github.com/chuckharmston/django-sunlightcongress
Author: Chuck Harmston
Author-email: chuck@chuckharmston.com
License: MIT
Keywords: america,united states,politics,congress,senate,house,sunlight,sunlight foundation
Platform: UNKNOWN
Classifier: Development Status :: 4 - Beta
Classifier: Environment :: Web Environment
Classifier: Framework :: Django
Classifier: Intended Audience :: Developers
Classifier: Intended Audience :: End Users/Desktop
Classifier: License :: OSI Approved :: MIT License
Classifier: Natural Language :: English
Classifier: Operating System :: OS Independent
Classifier: Programming Language :: Python
Classifier: Topic :: Communications
